jupyter_anywidget_window_ai/__init__.py
jupyter_anywidget_window_ai/panel.py
jupyter_anywidget_window_ai/static/utils.js
jupyter_anywidget_window_ai/static/widget.css
jupyter_anywidget_window_ai/static/widget.js
jupyter_anywidget_window_ai/static/windowai.css
jupyter_anywidget_window_ai/static/windowai.js
jupyter_anywidget_window_ai-0.0.3.dist-info/METADATA
jupyter_anywidget_window_ai-0.0.3.dist-info/WHEEL
jupyter_anywidget_window_ai-0.0.3.dist-info/licenses/LICENSE
jupyter_anywidget_window_ai-0.0.3.dist-info/RECORD
