Metadata-Version: 2.3
Name: jupyter_anywidget_window_ai
Version: 0.0.3
License-File: LICENSE
Requires-Dist: anywidget
Requires-Dist: sidecar
Provides-Extra: dev
Requires-Dist: jupyterlab; extra == 'dev'
Requires-Dist: watchfiles; extra == 'dev'
